plaidsync/__init__.py
plaidsync/config.py
plaidsync/main.py
plaidsync/plaidapi.py
plaidsync/transactionsdb.py
plaidsync/webserver.py
plaid_sync-0.0.1.dist-info/LICENSE
plaid_sync-0.0.1.dist-info/METADATA
plaid_sync-0.0.1.dist-info/WHEEL
plaid_sync-0.0.1.dist-info/entry_points.txt
plaid_sync-0.0.1.dist-info/top_level.txt
plaid_sync-0.0.1.dist-info/RECORD
