Metadata-Version: 2.1
Name: plaid-sync
Version: 0.0.1
Summary: Command-line interface to the Plaid API that synchronizes your bank/credit card transactions with a local SQLite database. Written in Python 3.
Home-page: https://github.com/henryrobbins/onm.git
Author: Matthew Bafford
Author-email: matthew@bafford.us
License: MIT License
Requires-Python: >=3.7
License-File: LICENSE
Requires-Dist: plaid-python ==7.1.0
